{"schemaVersion":1,"id":"0:2","collections":{"roads":[{"id":"southSpine","x":426,"y":640,"w":112,"h":800,"label":"Mourning Avenue","kind":"road"},{"id":"industrialBoulevard","x":0,"y":1136,"w":2400,"h":112,"label":"Blackwater Boulevard","kind":"road"}],"sidewalks":[{"id":"southSpine-west-walk","x":404,"y":640,"w":22,"h":800,"roadId":"southSpine"},{"id":"industrialBoulevard-north-walk","x":0,"y":1114,"w":2400,"h":22,"roadId":"industrialBoulevard"},{"id":"industrialBoulevard-south-walk","x":0,"y":1248,"w":2400,"h":22,"roadId":"industrialBoulevard"}],"crosswalks":[{"id":"cross-mourning-blackwater-across-vertical","x":426,"y":1182,"w":112,"h":20,"orientation":"horizontal"},{"id":"cross-mourning-blackwater-across-horizontal","x":472,"y":1136,"w":20,"h":112,"orientation":"vertical"}],"buildings":[{"id":"westMills","name":"WEST MILLS","x":82,"y":994,"w":304,"h":112,"color":1973016,"trim":8546381,"sign":"MILLS"},{"id":"southMortuary","name":"MUNICIPAL MORTUARY","x":82,"y":1282,"w":304,"h":118,"color":1644317,"trim":7300218,"sign":"MORTUARY"}],"sewerTunnels":[{"id":"sewerNorthSouth","x":426,"y":42,"w":92,"h":1358},{"id":"sewerBlackwater","x":72,"y":1136,"w":2240,"h":112}],"lights":[{"id":"lamp-blackwater-n-1","x":90,"y":1120,"radius":78,"name":"Blackwater north sidewalk light","layer":0},{"id":"lamp-blackwater-n-2","x":300,"y":1120,"radius":78,"name":"Blackwater north sidewalk light","layer":0},{"id":"lamp-blackwater-n-3","x":510,"y":1120,"radius":78,"name":"Blackwater north sidewalk light","layer":0},{"id":"lamp-blackwater-s-1","x":90,"y":1264,"radius":78,"name":"Blackwater south sidewalk light","layer":0},{"id":"lamp-blackwater-s-2","x":300,"y":1264,"radius":78,"name":"Blackwater south sidewalk light","layer":0},{"id":"lamp-blackwater-s-3","x":510,"y":1264,"radius":78,"name":"Blackwater south sidewalk light","layer":0}],"shadowZones":[{"id":"districtDarkness","x":0,"y":0,"w":2400,"h":1440,"name":"district darkness","strength":0.18}],"pedestrianRoutes":[{"id":"blackwater_loop","name":"Blackwater Boulevard loop","points":[{"x":560,"y":1120},{"x":1016,"y":1120},{"x":1088,"y":1120},{"x":1088,"y":1264,"crosswalk":true},{"x":560,"y":1264},{"x":482,"y":1264,"crosswalk":true},{"x":482,"y":1120,"crosswalk":true}]}],"navigationPoints":[{"x":482,"y":1192,"streamId":"navigationPoints:9"},{"x":482,"y":1264,"streamId":"navigationPoints:39"},{"x":482,"y":1120,"streamId":"navigationPoints:40"}]}}
